{
  "type": "FeatureCollection",
  "features": [
    {
      "type": "Feature",
      "properties": {},
      "geometry": {
        "type": "Point",
        "coordinates": [
          27.590049505233765,
          53.927724646237046
        ]
      }
    },
    {
      "type": "Feature",
      "properties": {},
      "geometry": {
        "type": "Point",
        "coordinates": [
          27.59344518184662,
          53.93149268335978
        ]
      }
    },
    {
      "type": "Feature",
      "properties": {},
      "geometry": {
        "type": "Point",
        "coordinates": [
          27.588633298873898,
          53.92515978599045
        ]
      }
    },
    {
      "type": "Feature",
      "properties": {},
      "geometry": {
        "type": "Point",
        "coordinates": [
          27.578998804092407,
          53.909615636392466
        ]
      }
    },
    {
      "type": "Feature",
      "properties": {},
      "geometry": {
        "type": "Point",
        "coordinates": [
          27.57134109735489,
          53.91108815556854
        ]
      }
    },
    {
      "type": "Feature",
      "properties": {},
      "geometry": {
        "type": "Point",
        "coordinates": [
          27.577563822269436,
          53.90155536011861
        ]
      }
    },
    {
      "type": "Feature",
      "properties": {},
      "geometry": {
        "type": "Point",
        "coordinates": [
          27.55192458629608,
          53.89188445293951
        ]
      }
    },
    {
      "type": "Feature",
      "properties": {},
      "geometry": {
        "type": "Point",
        "coordinates": [
          27.55689203739166,
          53.89992921114309
        ]
      }
    },
    {
      "type": "Feature",
      "properties": {},
      "geometry": {
        "type": "Point",
        "coordinates": [
          27.54921555519104,
          53.9051946070535
        ]
      }
    },
    {
      "type": "Feature",
      "properties": {},
      "geometry": {
        "type": "Point",
        "coordinates": [
          27.535514831542965,
          53.90772909283139
        ]
      }
    },
    {
      "type": "Feature",
      "properties": {},
      "geometry": {
        "type": "Point",
        "coordinates": [
          27.544972300529476,
          53.928188957536584
        ]
      }
    },
    {
      "type": "Feature",
      "properties": {},
      "geometry": {
        "type": "LineString",
        "coordinates": [
          [
            27.590028047561642,
            53.92769937744669
          ],
          [
            27.593493461608887,
            53.931407408830275
          ],
          [
            27.598042488098145,
            53.92994192302196
          ],
          [
            27.591819763183594,
            53.92413000711818
          ],
          [
            27.588343620300293,
            53.92519137389781
          ]
        ]
      }
    },
    {
      "type": "Feature",
      "properties": {},
      "geometry": {
        "type": "LineString",
        "coordinates": [
          [
            27.571263313293457,
            53.91108815556854
          ],
          [
            27.578773498535156,
            53.90974835484179
          ],
          [
            27.582507133483887,
            53.90833266963927
          ],
          [
            27.584524154663086,
            53.90491965982417
          ],
          [
            27.577486038208008,
            53.90160750962139
          ]
        ]
      }
    },
    {
      "type": "Feature",
      "properties": {},
      "geometry": {
        "type": "LineString",
        "coordinates": [
          [
            27.551651000976562,
            53.891972969510896
          ],
          [
            27.556757926940918,
            53.8999134076355
          ],
          [
            27.549118995666504,
            53.90517248492958
          ],
          [
            27.547155618667603,
            53.90505239319532
          ],
          [
            27.53997802734375,
            53.90631017896792
          ],
          [
            27.535085678100586,
            53.90744784202047
          ],
          [
            27.535514831542965,
            53.907722772609254
          ],
          [
            27.53920555114746,
            53.91450066136702
          ],
          [
            27.546586990356445,
            53.91768541519708
          ],
          [
            27.552852630615234,
            53.91798871241739
          ],
          [
            27.54495620727539,
            53.926176904600815
          ],
          [
            27.544784545898438,
            53.92829950708468
          ]
        ]
      }
    }
  ]
}